iterablepythonwrapper/__init__.py
iterablepythonwrapper/client.py
iterablepythonwrapper-1.1.dist-info/LICENSE.txt
iterablepythonwrapper-1.1.dist-info/METADATA
iterablepythonwrapper-1.1.dist-info/WHEEL
iterablepythonwrapper-1.1.dist-info/top_level.txt
iterablepythonwrapper-1.1.dist-info/RECORD
