Metadata-Version: 2.1
Name: iterablepythonwrapper
Version: 1.1
Summary: Python Client for the Iterable API
Home-page: https://github.com/carter-j-h/iterable-python-wrapper
Author: Carter Hickingbotham
Author-email: carterhickingbotham@gmail.com
License: MIT
Keywords: Iterable,API,Wrapper,Client,Python
Platform: UNKNOWN
Requires-Dist: peppercorn
